Metadata-Version: 1.0
Name: dsnd-distributions-udacity
Version: 0.1
Summary: dsnd_distributions udacity course
Home-page: UNKNOWN
Author: Alex McNulty
Author-email: UNKNOWN
License: UNKNOWN
Platform: UNKNOWN
